shasta_python/__init__.py
shasta_python/_client.py
shasta_python/_types.py
shasta_python/_utils.py
shasta_python/py.typed
shasta_python-0.0.2.dist-info/LICENSE
shasta_python-0.0.2.dist-info/METADATA
shasta_python-0.0.2.dist-info/WHEEL
shasta_python-0.0.2.dist-info/RECORD
