Metadata-Version: 2.1
Name: shasta-python
Version: 0.0.2
Summary: The official Python client for Krugle Shasta.
Home-page: https://krugle.ai/shasta
License: Apache-2.0
Author: Jason
Author-email: jason@aragoncg.com
Requires-Python: >=3.8,<4.0
Classifier: License :: OSI Approved :: Apache Software License
Classifier: Programming Language :: Python :: 3
Classifier: Programming Language :: Python :: 3.8
Classifier: Programming Language :: Python :: 3.9
Classifier: Programming Language :: Python :: 3.10
Classifier: Programming Language :: Python :: 3.11
Classifier: Programming Language :: Python :: 3.12
Requires-Dist: httpx (>=0.27.0,<0.28.0)
Requires-Dist: pydantic (>=2.9.0,<3.0.0)
Project-URL: Repository, https://github.com/krugle2/shasta-python
